colabservice/colabservice.py
colabservice-0.1.0.dist-info/METADATA
colabservice-0.1.0.dist-info/WHEEL
colabservice-0.1.0.dist-info/top_level.txt
colabservice-0.1.0.dist-info/RECORD
